slack_webhook/__init__.py
slack_webhook/slack_webhook.py
slack_webhook-1.0.7.dist-info/LICENSE.txt
slack_webhook-1.0.7.dist-info/METADATA
slack_webhook-1.0.7.dist-info/WHEEL
slack_webhook-1.0.7.dist-info/top_level.txt
slack_webhook-1.0.7.dist-info/RECORD
